<?xml version="1.0" encoding="UTF-8" ?>

<Stats>
<MachineGuid>91377b8b91263f79</MachineGuid>
<RecentSongScores>
<HighScoreForASongAndSteps>
<Song Dir='Songs/DDRMAX 1 _ 2/I Like To Move It/'/>
<Steps Difficulty='Easy' OnlineDescription='' OnlineHash='699594623' StepsType='dance-single'/>
<HighScore>
<Name></Name>
<Grade>Tier06</Grade>
<Score>789950</Score>
<PercentDP>0.635400</PercentDP>
<SurviveSeconds>102.628563</SurviveSeconds>
<MaxCombo>38</MaxCombo>
<StageAward>FullComboW3</StageAward>
<PeakComboAward>1000</PeakComboAward>
<Modifiers>FailImmediate, Overhead, Midi-note, Speed</Modifiers>
<DateTime>2023-11-26 19:42:30</DateTime>
<PlayerGuid></PlayerGuid>
<MachineGuid>91377b8b91263f79</MachineGuid>
<ProductID>1</ProductID>
<TapNoteScores>
<HitMine>0</HitMine>
<AvoidMine>0</AvoidMine>
<CheckpointMiss>0</CheckpointMiss>
<Miss>8</Miss>
<W5>0</W5>
<W4>4</W4>
<W3>34</W3>
<W2>30</W2>
<W1>29</W1>
<ProW5>0</ProW5>
<ProW4>0</ProW4>
<ProW3>0</ProW3>
<ProW2>0</ProW2>
<ProW1>0</ProW1>
<MaxScore>0</MaxScore>
<CheckpointHit>0</CheckpointHit>
</TapNoteScores>
<HoldNoteScores>
<LetGo>0</LetGo>
<Held>21</Held>
<MissedHold>2</MissedHold>
</HoldNoteScores>
<RadarValues>
<Stream>1.000000</Stream>
<Voltage>0.338471</Voltage>
<Air>0.428571</Air>
<Freeze>0.913043</Freeze>
<Chaos>0.635417</Chaos>
<Notes>117.000000</Notes>
<TapsAndHolds>97</TapsAndHolds>
<Jumps>19</Jumps>
<Holds>21</Holds>
<Mines>0</Mines>
<Hands>0</Hands>
<Rolls>0</Rolls>
<Lifts>0</Lifts>
<Fakes>0</Fakes>
</RadarValues>
<LifeRemainingSeconds>0.000000</LifeRemainingSeconds>
<Disqualified>0</Disqualified>
<Pad>33</Pad>
<StageGuid>f10edda6-bbc5-4d34-a126-0057b075f1ec</StageGuid>
<Guid>90cf6cae-724d-4cd7-a914-2ed8afa1b907</Guid>
</HighScore>
</HighScoreForASongAndSteps>
<HighScoreForASongAndSteps>
<Song Dir='Songs/DDRMAX 1 _ 2/I Like To Move It/'/>
<Steps Difficulty='Easy' OnlineDescription='' OnlineHash='699594623' StepsType='dance-single'/>
<HighScore>
<Name></Name>
<Grade>Tier07</Grade>
<Score>747860</Score>
<PercentDP>0.611900</PercentDP>
<SurviveSeconds>102.628563</SurviveSeconds>
<MaxCombo>13</MaxCombo>
<StageAward>FullComboW3</StageAward>
<PeakComboAward>1000</PeakComboAward>
<Modifiers>FailImmediate, Overhead, Midi-note, Speed</Modifiers>
<DateTime>2023-11-26 19:42:30</DateTime>
<PlayerGuid></PlayerGuid>
<MachineGuid>91377b8b91263f79</MachineGuid>
<ProductID>1</ProductID>
<TapNoteScores>
<HitMine>0</HitMine>
<AvoidMine>0</AvoidMine>
<CheckpointMiss>0</CheckpointMiss>
<Miss>17</Miss>
<W5>0</W5>
<W4>2</W4>
<W3>24</W3>
<W2>32</W2>
<W1>30</W1>
<ProW5>0</ProW5>
<ProW4>0</ProW4>
<ProW3>0</ProW3>
<ProW2>0</ProW2>
<ProW1>0</ProW1>
<MaxScore>0</MaxScore>
<CheckpointHit>0</CheckpointHit>
</TapNoteScores>
<HoldNoteScores>
<LetGo>0</LetGo>
<Held>19</Held>
<MissedHold>4</MissedHold>
</HoldNoteScores>
<RadarValues>
<Stream>1.000000</Stream>
<Voltage>0.131655</Voltage>
<Air>0.095238</Air>
<Freeze>0.826087</Freeze>
<Chaos>0.611979</Chaos>
<Notes>104.000000</Notes>
<TapsAndHolds>88</TapsAndHolds>
<Jumps>5</Jumps>
<Holds>19</Holds>
<Mines>0</Mines>
<Hands>0</Hands>
<Rolls>0</Rolls>
<Lifts>0</Lifts>
<Fakes>0</Fakes>
</RadarValues>
<LifeRemainingSeconds>0.000000</LifeRemainingSeconds>
<Disqualified>0</Disqualified>
<Pad>33</Pad>
<StageGuid>f10edda6-bbc5-4d34-a126-0057b075f1ec</StageGuid>
<Guid>4394deb5-86cb-4cc0-a0ef-bc822472446b</Guid>
</HighScore>
</HighScoreForASongAndSteps>
</RecentSongScores>
</Stats>
